spil_hamlet_conf/spil_qtui_conf.py
spil_hamlet_conf/hamlet_plugins/__init__.py
spil_hamlet_conf/hamlet_plugins/actions/__init__.py
spil_hamlet_conf/hamlet_plugins/actions/action_handler.py
spil_hamlet_conf/hamlet_plugins/actions/example_actions.py
spil_hamlet_conf/hamlet_plugins/actions/utils.py
spil_ui/__init__.py
spil_ui/bar/__init__.py
spil_ui/bar/ui/__init__.py
spil_ui/bar/ui/bar.py
spil_ui/bar/ui/bar_qt_helper.py
spil_ui/browser/__init__.py
spil_ui/browser/ui/__init__.py
spil_ui/browser/ui/action_handler.py
spil_ui/browser/ui/browser.py
spil_ui/browser/ui/qt_helper.py
spil_ui/browser/ui/qt/browser.ui
spil_ui/conf/__init__.py
spil_ui/conf/qtui_conf_load.py
spil_ui/util/__init__.py
spil_ui/util/clear.py
spil_ui/util/dialogs.py
spil_ui/util/parsedatetime.py
spil_ui/util/time_tools.py
spil_ui-0.1.0.dist-info/METADATA
spil_ui-0.1.0.dist-info/WHEEL
spil_ui-0.1.0.dist-info/licenses/LICENSE
spil_ui-0.1.0.dist-info/RECORD
