Metadata-Version: 2.1
Name: spil_ui
Version: 0.1.0
Summary: Qt UI for Spil, The Simple Pipeline Lib.
Project-URL: Homepage, https://github.com/MichaelHaussmann/spil_ui
Project-URL: Documentation, https://spil.readthedocs.io
Author-email: Michael Haussmann <spil@xeo.info>
License: MIT License
License-File: LICENSE
Keywords: cg,cg-pipeline,path templates,vfx,vfx-pipeline
Classifier: Development Status :: 4 - Beta
Classifier: Intended Audience :: Developers
Classifier: License :: OSI Approved :: MIT License
Classifier: Natural Language :: English
Classifier: Operating System :: OS Independent
Classifier: Programming Language :: Python
Classifier: Programming Language :: Python :: 3
Classifier: Programming Language :: Python :: 3.7
Classifier: Topic :: Software Development
Classifier: Topic :: Software Development :: Libraries
Requires-Python: >=3.7
Requires-Dist: qdarkstyle
Requires-Dist: qtpy
Requires-Dist: spil
Provides-Extra: dev
Requires-Dist: pytest; extra == 'dev'
